pyprocreate/ProcreateProject.py
pyprocreate/__init__.py
pyprocreate-0.1.0.dist-info/LICENSE
pyprocreate-0.1.0.dist-info/METADATA
pyprocreate-0.1.0.dist-info/WHEEL
pyprocreate-0.1.0.dist-info/top_level.txt
pyprocreate-0.1.0.dist-info/RECORD
