Metadata-Version: 2.1
Name: pyprocreate
Version: 0.1.0
Summary: A package to parse and interact with Apple's Procreate (.pro) file format.
Home-page: https://gitlab.com/inklabapp/pyprocreate
Author: InkLab
Author-email: inklabapp@gmail.com
License: MIT License
Platform: UNKNOWN
Classifier: Programming Language :: Python :: 3
Classifier: License :: OSI Approved :: MIT License
Classifier: Operating System :: OS Independent
Requires-Dist: biplist
Requires-Dist: pillow
Requires-Dist: python-lzo
